pitchcontext/ComputePitchContext.py
pitchcontext/PCParameters.py
pitchcontext/__init__.py
pitchcontext/base40.py
pitchcontext/models.py
pitchcontext/pitchcontext.py
pitchcontext/song.py
pitchcontext/visualize.py
pitchcontext-0.1.11.dist-info/LICENSE
pitchcontext-0.1.11.dist-info/METADATA
pitchcontext-0.1.11.dist-info/WHEEL
pitchcontext-0.1.11.dist-info/RECORD
