Metadata-Version: 2.1
Name: pitchcontext
Version: 0.1.11
Summary: Library for melody analysis based on pitch context vectors.
Author: Peter van Kranenburg
Author-email: p.vankranenburg@uu.nl
Requires-Python: >=3.8, !=2.7.*, !=3.0.*, !=3.1.*, !=3.2.*, !=3.3.*, !=3.4.*, !=3.5.*, !=3.6.*, !=3.7.*
Classifier: Programming Language :: Python :: 3
Classifier: Programming Language :: Python :: 3.8
Classifier: Programming Language :: Python :: 3.9
Classifier: Programming Language :: Python :: 3.10
Classifier: Programming Language :: Python :: 3.11
Classifier: Programming Language :: Python :: 3.12
Requires-Dist: IPython (>=7.19,<8.0)
Requires-Dist: matplotlib (>=3.3,<4.0)
Requires-Dist: music21 (>=8.0,<9.0)
Requires-Dist: numpy (>=1.19,<2.0)
Requires-Dist: seaborn (>=0.12.1,<0.13.0)
